{
    "name":"record",
    "type":"record",
    "field_specification":{
        "name":"fspec",
        "type":"extendable_bits",
        "reverse_bits":true,
        "data_type":"bitfield"
    },
    "uap":[
        "010",
        "040",
        "161",
        "015",
        "071",
        "130",
        "131",
        "FX",
        "072",
        "150",
        "151",
        "080",
        "073",
        "074",
        "075",
        "FX",
        "076",
        "140",
        "090",
        "210",
        "070",
        "230",
        "145",
        "FX",
        "152",
        "200",
        "155",
        "157",
        "160",
        "165",
        "077",
        "FX",
        "170",
        "020",
        "220",
        "146",
        "148",
        "110",
        "016",
        "FX",
        "008",
        "271",
        "132",
        "250",
        "260",
        "400",
        "295",
        "FX",
        "-",
        "-",
        "-",
        "-",
        "-",
        "RE",
        "SP",
        "FX"
    ],
    "items":[
        {
            "name":"008",
            "type":"item",
            "data_fields":[
                {
                    "name":"Aircraft Operational Status",
                    "type":"fixed_bitfield",
                    "length":1,
                    "items":[
                        {
                            "name":"RA",
                            "type":"fixed_bits",
                            "start_bit":7,
                            "bit_length":1
                        },
                        {
                            "name":"TC",
                            "type":"fixed_bits",
                            "start_bit":5,
                            "bit_length":2
                        },
                        {
                            "name":"TS",
                            "type":"fixed_bits",
                            "start_bit":4,
                            "bit_length":1
                        },
                        {
                            "name":"ARV",
                            "type":"fixed_bits",
                            "start_bit":3,
                            "bit_length":1
                        },
                        {
                            "name":"CDTI/A",
                            "type":"fixed_bits",
                            "start_bit":2,
                            "bit_length":1
                        },
                        {
                            "name":"Not TCAS",
                            "type":"fixed_bits",
                            "start_bit":1,
                            "bit_length":1
                        },
                        {
                            "name":"SA",
                            "type":"fixed_bits",
                            "start_bit":0,
                            "bit_length":1
                        }
                    ]
                }
            ]
        },
        {
            "name":"010",
            "type":"item",
            "data_fields":[
                {
                    "name":"SAC",
                    "type":"fixed_bytes",
                    "length":1,
                    "data_type":"uint"
                },
                {
                    "name":"SUC",
                    "type":"fixed_bytes",
                    "length":1,
                    "data_type":"uint"
                }
            ]
        },
        {
            "name":"015",
            "type":"item",
            "data_fields":[
                {
                    "name":"Service Identification",
                    "type":"fixed_bytes",
                    "length":1,
                    "data_type":"uint"
                }
            ]
        },
        {
            "name":"016",
            "type":"item",
            "data_fields":[
                {
                    "name":"RP",
                    "type":"fixed_bytes",
                    "length":1,
                    "data_type":"uint",
                    "lsb":0.5
                }
            ]
        },
        {
            "name":"020",
            "type":"item",
            "data_fields":[
                {
                    "name":"ECAT",
                    "type":"fixed_bytes",
                    "length":1,
                    "data_type":"uint"
                }
            ]
        },
        {
            "name":"040",
            "type":"item",
            "data_fields":[
                {
                    "name":"Target Report Descriptor",
                    "type":"fixed_bitfield",
                    "length":1,
                    "items":[
                        {
                            "name":"ATP",
                            "type":"fixed_bits",
                            "start_bit":5,
                            "bit_length":3
                        },
                        {
                            "name":"ARC",
                            "type":"fixed_bits",
                            "start_bit":3,
                            "bit_length":2
                        },
                        {
                            "name":"RC",
                            "type":"fixed_bits",
                            "start_bit":2,
                            "bit_length":1
                        },
                        {
                            "name":"RAB",
                            "type":"fixed_bits",
                            "start_bit":1,
                            "bit_length":1
                        },
                        {
                            "name":"FX",
                            "type":"fixed_bits",
                            "start_bit":0,
                            "bit_length":1
                        }
                    ]
                },
                {
                    "name":"Target Report Descriptor First Extension",
                    "type":"fixed_bitfield",
                    "length":1,
                    "optional":true,
                    "optional_variable_name":"FX",
                    "optional_variable_value":1,
                    "items":[
                        {
                            "name":"DCR",
                            "type":"fixed_bits",
                            "start_bit":7,
                            "bit_length":1
                        },
                        {
                            "name":"GBS",
                            "type":"fixed_bits",
                            "start_bit":6,
                            "bit_length":1
                        },
                        {
                            "name":"SIM",
                            "type":"fixed_bits",
                            "start_bit":5,
                            "bit_length":1
                        },
                        {
                            "name":"TST",
                            "type":"fixed_bits",
                            "start_bit":4,
                            "bit_length":1
                        },
                        {
                            "name":"SAA",
                            "type":"fixed_bits",
                            "start_bit":3,
                            "bit_length":1
                        },
                        {
                            "name":"CL",
                            "type":"fixed_bits",
                            "start_bit":1,
                            "bit_length":2
                        },
                        {
                            "name":"FX2",
                            "type":"fixed_bits",
                            "start_bit":0,
                            "bit_length":1
                        }
                    ]
                },
                {
                    "name":"Target Report Descriptor Second Extension : Error Conditions",
                    "type":"fixed_bitfield",
                    "length":1,
                    "optional":true,
                    "optional_variable_name":"FX2",
                    "optional_variable_value":1,
                    "items":[
                        {
                            "name":"IPC",
                            "type":"fixed_bits",
                            "start_bit":5,
                            "bit_length":1
                        },
                        {
                            "name":"NOGO",
                            "type":"fixed_bits",
                            "start_bit":4,
                            "bit_length":1
                        },
                        {
                            "name":"CPR",
                            "type":"fixed_bits",
                            "start_bit":3,
                            "bit_length":1
                        },
                        {
                            "name":"LDPJ",
                            "type":"fixed_bits",
                            "start_bit":2,
                            "bit_length":1
                        },
                        {
                            "name":"RCF",
                            "type":"fixed_bits",
                            "start_bit":1,
                            "bit_length":1
                        },
                        {
                            "name":"FX3",
                            "type":"fixed_bits",
                            "start_bit":0,
                            "bit_length":1
                        }
                    ]
                }
            ]
        },
        {
            "name":"070",
            "type":"item",
            "data_fields":[
                {
                    "name":"Mode 3/A Code in Octal Representation",
                    "type":"fixed_bitfield",
                    "length":2,
                    "items":[
                        {
                            "name":"Mode-3/A",
                            "type":"fixed_bits",
                            "data_type":"digits",
                            "start_bit":0,
                            "bit_length":12,
                            "num_digits":4,
                            "digit_bit_length":3
                        }
                    ]
                }
            ]
        },
        {
            "name":"071",
            "type":"item",
            "data_fields":[
                {
                    "name":"Time of Applicability for Position",
                    "type":"fixed_bytes",
                    "length":3,
                    "data_type":"uint",
                    "lsb":0.0078125
                }
            ]
        },
        {
            "name":"072",
            "type":"item",
            "data_fields":[
                {
                    "name":"Time of Applicability for Velocity",
                    "type":"fixed_bytes",
                    "length":3,
                    "data_type":"uint",
                    "lsb":0.0078125
                }
            ]
        },
        {
            "name":"073",
            "type":"item",
            "data_fields":[
                {
                    "name":"Time of Message Reception for Position",
                    "type":"fixed_bytes",
                    "length":3,
                    "data_type":"uint",
                    "lsb":0.0078125
                }
            ]
        },
        {
            "name":"074",
            "type":"item",
            "data_fields":[
                {
                    "name":"Time of Message Reception of Position-High Precision",
                    "type":"fixed_bitfield",
                    "length":4,
                    "items":[
                        {
                            "name":"FSI",
                            "type":"fixed_bits",
                            "start_bit":30,
                            "bit_length":2
                        },
                        {
                            "name":"Time of Message Reception of Position - high precision",
                            "type":"fixed_bits",
                            "start_bit":0,
                            "bit_length":30,
                            "lsb":9.3132257e-10
                        }
                    ]
                }
            ]
        },
        {
            "name":"075",
            "type":"item",
            "data_fields":[
                {
                    "name":"Time of Message Reception of Velocity",
                    "type":"fixed_bytes",
                    "length":3,
                    "data_type":"uint",
                    "lsb":0.0078125
                }
            ]
        },
        {
            "name":"076",
            "type":"item",
            "data_fields":[
                {
                    "name":"Time of Message Reception of Velocity-High Precision",
                    "type":"fixed_bitfield",
                    "length":4,
                    "items":[
                        {
                            "name":"FSI",
                            "type":"fixed_bits",
                            "start_bit":30,
                            "bit_length":2
                        },
                        {
                            "name":"Time of Message Reception of Velocity - high precision",
                            "type":"fixed_bits",
                            "start_bit":0,
                            "bit_length":30,
                            "lsb":9.3132257e-10
                        }
                    ]
                }
            ]
        },
        {
            "name":"077",
            "type":"item",
            "data_fields":[
                {
                    "name":"Time Of ASTERIX Report Transmission",
                    "type":"fixed_bytes",
                    "length":3,
                    "data_type":"uint",
                    "lsb":0.0078125
                }
            ]
        },
        {
            "name":"080",
            "type":"item",
            "data_fields":[
                {
                    "name":"Target Address",
                    "type":"fixed_bytes",
                    "length":3,
                    "data_type":"uint"
                }
            ]
        },
        {
            "name":"090",
            "type":"item",
            "data_fields":[
                {
                    "name":"Quality Indicators",
                    "type":"fixed_bitfield",
                    "length":1,
                    "items":[
                        {
                            "name":"NUCr or NACv",
                            "type":"fixed_bits",
                            "start_bit":5,
                            "bit_length":3
                        },
                        {
                            "name":"NUCp or NIC",
                            "type":"fixed_bits",
                            "start_bit":1,
                            "bit_length":4
                        },
                        {
                            "name":"FX",
                            "type":"fixed_bits",
                            "start_bit":0,
                            "bit_length":1
                        }
                    ]
                },
                {
                    "name":"Quality Indicators First Extension : Navigation Accuracy Category for Position",
                    "type":"fixed_bitfield",
                    "length":1,
                    "optional":true,
                    "optional_variable_name":"FX",
                    "optional_variable_value":1,
                    "items":[
                        {
                            "name":"NICbaro",
                            "type":"fixed_bits",
                            "start_bit":7,
                            "bit_length":1
                        },
                        {
                            "name":"SIL",
                            "type":"fixed_bits",
                            "start_bit":5,
                            "bit_length":2
                        },
                        {
                            "name":"NACp",
                            "type":"fixed_bits",
                            "start_bit":1,
                            "bit_length":4
                        },
                        {
                            "name":"FX2",
                            "type":"fixed_bits",
                            "start_bit":0,
                            "bit_length":1
                        }
                    ]
                },
                {
                    "name":"Quality Indicators Second Extension : Position Quality Indicators",
                    "type":"fixed_bitfield",
                    "length":1,
                    "optional":true,
                    "optional_variable_name":"FX2",
                    "optional_variable_value":1,
                    "items":[
                        {
                            "name":"SIL-Supplement",
                            "type":"fixed_bits",
                            "start_bit":5,
                            "bit_length":1
                        },
                        {
                            "name":"SDA",
                            "type":"fixed_bits",
                            "start_bit":3,
                            "bit_length":2
                        },
                        {
                            "name":"GVA",
                            "type":"fixed_bits",
                            "start_bit":1,
                            "bit_length":2
                        },
                        {
                            "name":"FX3",
                            "type":"fixed_bits",
                            "start_bit":0,
                            "bit_length":1
                        }
                    ]
                },
                {
                    "name":"Quality Indicators Third Extension : Position Quality Indicators",
                    "type":"fixed_bitfield",
                    "length":1,
                    "optional":true,
                    "optional_variable_name":"FX3",
                    "optional_variable_value":1,
                    "items":[
                        {
                            "name":"PIC",
                            "type":"fixed_bits",
                            "start_bit":4,
                            "bit_length":4
                        },
                        {
                            "name":"FX4",
                            "type":"fixed_bits",
                            "start_bit":0,
                            "bit_length":1
                        }
                    ]
                }
            ]
        },
        {
            "name":"110",
            "type":"item",
            "data_fields":[
                {
                    "name":"Trajectory Intent",
                    "type":"compound",
                    "field_specification":{
                        "name":"available",
                        "type":"extendable_bits",
                        "data_type":"bitfield"
                    },
                    "items":[
                        {
                            "name":"TIS",
                            "type":"optional_item",
                            "optional_bitfield_name":"available",
                            "optional_bitfield_index":7,
                            "data_fields":[
                                {
                                    "name":"Trajectory Intent Status",
                                    "type":"fixed_bitfield",
                                    "length":1,
                                    "items":[
                                        {
                                            "name":"NAV",
                                            "type":"fixed_bits",
                                            "start_bit":7,
                                            "bit_length":1
                                        },
                                        {
                                            "name":"NVB",
                                            "type":"fixed_bits",
                                            "start_bit":6,
                                            "bit_length":1
                                        }
                                    ]
                                }
                            ]
                        },
                        {
                            "name":"TID",
                            "type":"optional_item",
                            "optional_bitfield_name":"available",
                            "optional_bitfield_index":6,
                            "data_fields":[
                                {
                                    "name":"rep",
                                    "type":"repetitive",
                                    "repetition_item":{
                                        "name":"REP",
                                        "type":"fixed_bytes",
                                        "length":1,
                                        "data_type":"uint"
                                    },
                                    "items":[
                                        {
                                            "name":"TID1",
                                            "type":"fixed_bitfield",
                                            "length":1,
                                            "items":[
                                                {
                                                    "name":"TCA",
                                                    "type":"fixed_bits",
                                                    "start_bit":7,
                                                    "bit_length":1
                                                },
                                                {
                                                    "name":"NC",
                                                    "type":"fixed_bits",
                                                    "start_bit":6,
                                                    "bit_length":1
                                                },
                                                {
                                                    "name":"TCP number",
                                                    "type":"fixed_bits",
                                                    "start_bit":0,
                                                    "bit_length":6
                                                }
                                            ]
                                        },
                                        {
                                            "name":"Altitude",
                                            "type":"fixed_bytes",
                                            "length":2,
                                            "data_type":"int",
                                            "lsb":10.0
                                        },
                                        {
                                            "name":"Latitude in WGS - 84",
                                            "type":"fixed_bytes",
                                            "length":3,
                                            "data_type":"int",
                                            "lsb":0.00002145767
                                        },
                                        {
                                            "name":"Longitude in WGS - 84",
                                            "type":"fixed_bytes",
                                            "length":3,
                                            "data_type":"int",
                                            "lsb":0.00002145767
                                        },
                                        {
                                            "name":"TID2",
                                            "type":"fixed_bitfield",
                                            "length":1,
                                            "items":[
                                                {
                                                    "name":"Point Type",
                                                    "type":"fixed_bits",
                                                    "start_bit":4,
                                                    "bit_length":4
                                                },
                                                {
                                                    "name":"TD",
                                                    "type":"fixed_bits",
                                                    "start_bit":2,
                                                    "bit_length":2
                                                },
                                                {
                                                    "name":"TRA",
                                                    "type":"fixed_bits",
                                                    "start_bit":1,
                                                    "bit_length":1
                                                },
                                                {
                                                    "name":"TOA",
                                                    "type":"fixed_bits",
                                                    "start_bit":0,
                                                    "bit_length":1
                                                }
                                            ]
                                        },
                                        {
                                            "name":"TOV",
                                            "type":"fixed_bytes",
                                            "length":3,
                                            "data_type":"uint",
                                            "lsb":1.0
                                        },
                                        {
                                            "name":"TTR",
                                            "type":"fixed_bytes",
                                            "length":2,
                                            "data_type":"uint",
                                            "lsb":0.01
                                        }
                                    ]
                                }
                            ]
                        }
                    ]
                }
            ]
        },
        {
            "name":"130",
            "type":"item",
            "data_fields":[
                {
                    "name":"Latitude in WGS - 84",
                    "type":"fixed_bytes",
                    "length":3,
                    "data_type":"int",
                    "lsb":0.00002145767
                },
                {
                    "name":"Longitude in WGS - 84",
                    "type":"fixed_bytes",
                    "length":3,
                    "data_type":"int",
                    "lsb":0.00002145767
                }
            ]
        },
        {
            "name":"131",
            "type":"item",
            "data_fields":[
                {
                    "name":"Latitude in WGS - 84",
                    "type":"fixed_bytes",
                    "length":4,
                    "data_type":"int",
                    "lsb":1.67638063e-7
                },
                {
                    "name":"Longitude in WGS - 84",
                    "type":"fixed_bytes",
                    "length":4,
                    "data_type":"int",
                    "lsb":1.67638063e-7
                }
            ]
        },
        {
            "name":"132",
            "type":"item",
            "data_fields":[
                {
                    "name":"MAM",
                    "type":"fixed_bytes",
                    "length":1,
                    "data_type":"int",
                    "lsb":1.0
                }
            ]
        },
        {
            "name":"140",
            "type":"item",
            "data_fields":[
                {
                    "name":"Geometric Height (GH)",
                    "type":"fixed_bytes",
                    "length":2,
                    "data_type":"int",
                    "lsb":6.25
                }
            ]
        },
        {
            "name":"145",
            "type":"item",
            "data_fields":[
                {
                    "name":"Flight Level",
                    "type":"fixed_bytes",
                    "length":2,
                    "data_type":"int",
                    "lsb":0.25
                }
            ]
        },
        {
            "name":"146",
            "type":"item",
            "data_fields":[
                {
                    "name":"Selected Altitude",
                    "type":"fixed_bitfield",
                    "length":2,
                    "items":[
                        {
                            "name":"SAS",
                            "type":"fixed_bits",
                            "start_bit":15,
                            "bit_length":1
                        },
                        {
                            "name":"Source",
                            "type":"fixed_bits",
                            "start_bit":13,
                            "bit_length":2
                        },
                        {
                            "name":"Altitude",
                            "type":"fixed_bits",
                            "start_bit":0,
                            "bit_length":13,
                            "data_type":"int",
                            "lsb":25.0
                        }
                    ]
                }
            ]
        },
        {
            "name":"148",
            "type":"item",
            "data_fields":[
                {
                    "name":"Final State Selected Altitude",
                    "type":"fixed_bitfield",
                    "length":2,
                    "items":[
                        {
                            "name":"MV",
                            "type":"fixed_bits",
                            "start_bit":15,
                            "bit_length":1
                        },
                        {
                            "name":"AH",
                            "type":"fixed_bits",
                            "start_bit":14,
                            "bit_length":1
                        },
                        {
                            "name":"AM",
                            "type":"fixed_bits",
                            "start_bit":13,
                            "bit_length":1
                        },
                        {
                            "name":"Altitude",
                            "type":"fixed_bits",
                            "start_bit":0,
                            "bit_length":13,
                            "data_type":"int",
                            "lsb":25.0
                        }
                    ]
                }
            ]
        },
        {
            "name":"150",
            "type":"item",
            "data_fields":[
                {
                    "name":"Air Speed",
                    "type":"fixed_bitfield",
                    "length":2,
                    "items":[
                        {
                            "name":"IM",
                            "type":"fixed_bits",
                            "start_bit":15,
                            "bit_length":1
                        },
                        {
                            "name":"Air Speed_TODO",
                            "type":"fixed_bits",
                            "start_bit":0,
                            "bit_length":15
                        }
                    ]
                }
            ]
        },
        {
            "name":"151",
            "type":"item",
            "data_fields":[
                {
                    "name":"True Airspeed",
                    "type":"fixed_bitfield",
                    "length":2,
                    "items":[
                        {
                            "name":"RE",
                            "type":"fixed_bits",
                            "start_bit":15,
                            "bit_length":1
                        },
                        {
                            "name":"True Air Speed",
                            "type":"fixed_bits",
                            "start_bit":0,
                            "bit_length":15,
                            "lsb":1.0
                        }
                    ]
                }
            ]
        },
        {
            "name":"152",
            "type":"item",
            "data_fields":[
                {
                    "name":"Magnetic Heading",
                    "type":"fixed_bytes",
                    "length":2,
                    "data_type":"int",
                    "lsb":0.00549316406
                }
            ]
        },
        {
            "name":"157",
            "type":"item",
            "data_fields":[
                {
                    "name":"Barometric Vertical Rate",
                    "type":"fixed_bitfield",
                    "length":2,
                    "items":[
                        {
                            "name":"RE",
                            "type":"fixed_bits",
                            "start_bit":15,
                            "bit_length":1
                        },
                        {
                            "name":"Barometric Vertical Rate",
                            "type":"fixed_bits",
                            "start_bit":0,
                            "bit_length":15,
                            "data_type":"int",
                            "lsb":6.25
                        }
                    ]
                }
            ]
        },
        {
            "name":"160",
            "type":"item",
            "data_fields":[
                {
                    "name":"Ground Speed",
                    "type":"fixed_bitfield",
                    "length":2,
                    "items":[
                        {
                            "name":"RE",
                            "type":"fixed_bits",
                            "start_bit":15,
                            "bit_length":1
                        },
                        {
                            "name":"Ground Speed",
                            "type":"fixed_bits",
                            "start_bit":0,
                            "bit_length":15,
                            "lsb":0.00006103515
                        }
                    ]
                },
                {
                    "name":"Track Angle",
                    "type":"fixed_bytes",
                    "length":2,
                    "data_type":"uint",
                    "lsb":0.00549316406
                }
            ]
        },
        {
            "name":"161",
            "type":"item",
            "data_fields":[
                {
                    "name":"Track Number",
                    "type":"fixed_bytes",
                    "length":2,
                    "data_type":"uint"
                }
            ]
        },
        {
            "name":"165",
            "type":"item",
            "data_fields":[
                {
                    "name":"Track Angle Rate",
                    "type":"fixed_bitfield",
                    "length":2,
                    "items":[
                        {
                            "name":"TAR",
                            "type":"fixed_bits",
                            "start_bit":0,
                            "bit_length":10,
                            "data_type":"int",
                            "lsb":0.03125
                        }
                    ]
                }
            ]
        },
        {
            "name":"170",
            "type":"item",
            "data_fields":[
                {
                    "name":"Target Identification",
                    "type":"fixed_bitfield",
                    "length":6,
                    "items":[
                        {
                            "name":"Target Identification",
                            "type":"fixed_bits",
                            "data_type":"characters",
                            "start_bit":0,
                            "bit_length":47,
                            "num_characters":8,
                            "character_bit_length":6
                        }
                    ]
                }
            ]
        },
        {
            "name":"200",
            "type":"item",
            "data_fields":[
                {
                    "name":"Target Status",
                    "type":"fixed_bitfield",
                    "length":1,
                    "items":[
                        {
                            "name":"ICF",
                            "type":"fixed_bits",
                            "start_bit":7,
                            "bit_length":1
                        },
                        {
                            "name":"LNAV",
                            "type":"fixed_bits",
                            "start_bit":6,
                            "bit_length":1
                        },
                        {
                            "name":"PS",
                            "type":"fixed_bits",
                            "start_bit":2,
                            "bit_length":3
                        },
                        {
                            "name":"SS",
                            "type":"fixed_bits",
                            "start_bit":0,
                            "bit_length":2
                        }
                    ]
                }
            ]
        },
        {
            "name":"210",
            "type":"item",
            "data_fields":[
                {
                    "name":"MOPS Version",
                    "type":"fixed_bitfield",
                    "length":1,
                    "items":[
                        {
                            "name":"VNC",
                            "type":"fixed_bits",
                            "start_bit":6,
                            "bit_length":1
                        },
                        {
                            "name":"VN",
                            "type":"fixed_bits",
                            "start_bit":3,
                            "bit_length":3
                        },
                        {
                            "name":"LTT",
                            "type":"fixed_bits",
                            "start_bit":0,
                            "bit_length":3
                        }
                    ]
                }
            ]
        },
        {
            "name":"220",
            "type":"item",
            "data_fields":[
                {
                    "name":"Met Information",
                    "type":"compound",
                    "field_specification":{
                        "name":"available",
                        "type":"extendable_bits",
                        "data_type":"bitfield"
                    },
                    "items":[
                        {
                            "name":"WS",
                            "type":"optional_item",
                            "optional_bitfield_name":"available",
                            "optional_bitfield_index":7,
                            "data_fields":[
                                {
                                    "name":"Wind Speed",
                                    "type":"fixed_bytes",
                                    "length":2,
                                    "data_type":"uint",
                                    "lsb":1.0
                                }
                            ]
                        },
                        {
                            "name":"WD",
                            "type":"optional_item",
                            "optional_bitfield_name":"available",
                            "optional_bitfield_index":6,
                            "data_fields":[
                                {
                                    "name":"Wind Direction",
                                    "type":"fixed_bytes",
                                    "length":2,
                                    "data_type":"uint",
                                    "lsb":1.0
                                }
                            ]
                        },
                        {
                            "name":"TMP",
                            "type":"optional_item",
                            "optional_bitfield_name":"available",
                            "optional_bitfield_index":5,
                            "data_fields":[
                                {
                                    "name":"Temperature",
                                    "type":"fixed_bytes",
                                    "length":2,
                                    "data_type":"uint",
                                    "lsb":0.25
                                }
                            ]
                        },
                        {
                            "name":"TRB",
                            "type":"optional_item",
                            "optional_bitfield_name":"available",
                            "optional_bitfield_index":4,
                            "data_fields":[
                                {
                                    "name":"Turbulence",
                                    "type":"fixed_bytes",
                                    "length":1,
                                    "data_type":"uint"
                                }
                            ]
                        }
                    ]
                }
            ]
        },
        {
            "name":"230",
            "type":"item",
            "data_fields":[
                {
                    "name":"Roll Angle",
                    "type":"fixed_bytes",
                    "length":2,
                    "data_type":"int",
                    "lsb":0.01
                }
            ]
        },
        {
            "name":"250",
            "type":"item",
            "data_fields":[
                {
                    "name":"rep",
                    "type":"repetitive",
                    "repetition_item":{
                        "name":"REP",
                        "type":"fixed_bytes",
                        "length":1,
                        "data_type":"uint"
                    },
                    "items":[
                        {
                            "name":"MB DATA",
                            "type":"fixed_bytes",
                            "length":7,
                            "data_type":"bin"
                        },
                        {
                            "name":"MB Data Address",
                            "type":"fixed_bitfield",
                            "length":1,
                            "items":[
                                {
                                    "name":"BDS1",
                                    "type":"fixed_bits",
                                    "start_bit":4,
                                    "bit_length":4
                                },
                                {
                                    "name":"BDS2",
                                    "type":"fixed_bits",
                                    "start_bit":0,
                                    "bit_length":4
                                }
                            ]
                        }
                    ]
                }
            ]
        },
        {
            "name":"260",
            "type":"item",
            "data_fields":[
                {
                    "name":"ACAS Resolution Advisory Report",
                    "type":"fixed_bytes",
                    "length":7,
                    "data_type":"bin"
                }
            ]
        },
        {
            "name":"271",
            "type":"item",
            "data_fields":[
                {
                    "name":"Surface Capabilities and Characteristics",
                    "type":"fixed_bitfield",
                    "length":1,
                    "items":[
                        {
                            "name":"POA",
                            "type":"fixed_bits",
                            "start_bit":5,
                            "bit_length":1
                        },
                        {
                            "name":"CDTI/S",
                            "type":"fixed_bits",
                            "start_bit":4,
                            "bit_length":1
                        },
                        {
                            "name":"B2 low",
                            "type":"fixed_bits",
                            "start_bit":3,
                            "bit_length":1
                        },
                        {
                            "name":"RAS",
                            "type":"fixed_bits",
                            "start_bit":2,
                            "bit_length":1
                        },
                        {
                            "name":"IDENT",
                            "type":"fixed_bits",
                            "start_bit":1,
                            "bit_length":1
                        },
                        {
                            "name":"FX",
                            "type":"fixed_bits",
                            "start_bit":0,
                            "bit_length":1
                        }
                    ]
                },
                {
                    "name":"Surface Capabilities and Characteristics First Extension : Length / Width of Aircraft",
                    "type":"fixed_bitfield",
                    "length":1,
                    "optional":true,
                    "optional_variable_name":"FX",
                    "optional_variable_value":1,
                    "items":[
                        {
                            "name":"L + W",
                            "type":"fixed_bits",
                            "start_bit":0,
                            "bit_length":4
                        }
                    ]
                }
            ]
        },
        {
            "name":"295",
            "type":"item",
            "data_fields":[
                {
                    "name":"Data Ages",
                    "type":"compound",
                    "field_specification":{
                        "name":"available",
                        "type":"extendable_bits",
                        "data_type":"bitfield"
                    },
                    "items":[
                        {
                            "name":"Aircraft Operational Status",
                            "type":"optional_item",
                            "optional_bitfield_name":"available",
                            "optional_bitfield_index":31,
                            "data_fields":[
                                {
                                    "name":"Age",
                                    "type":"fixed_bytes",
                                    "data_type":"uint",
                                    "length":1,
                                    "lsb":0.1
                                }
                            ]
                        },
                        {
                            "name":"Target Report Descriptor",
                            "type":"optional_item",
                            "optional_bitfield_name":"available",
                            "optional_bitfield_index":30,
                            "data_fields":[
                                {
                                    "name":"Age",
                                    "type":"fixed_bytes",
                                    "data_type":"uint",
                                    "length":1,
                                    "lsb":0.1
                                }
                            ]
                        },
                        {
                            "name":"Mode 3/A",
                            "type":"optional_item",
                            "optional_bitfield_name":"available",
                            "optional_bitfield_index":29,
                            "data_fields":[
                                {
                                    "name":"Age",
                                    "type":"fixed_bytes",
                                    "data_type":"uint",
                                    "length":1,
                                    "lsb":0.1
                                }
                            ]
                        },
                        {
                            "name":"Quality Indicators",
                            "type":"optional_item",
                            "optional_bitfield_name":"available",
                            "optional_bitfield_index":28,
                            "data_fields":[
                                {
                                    "name":"Age",
                                    "type":"fixed_bytes",
                                    "data_type":"uint",
                                    "length":1,
                                    "lsb":0.1
                                }
                            ]
                        },
                        {
                            "name":"Trajectory Intent",
                            "type":"optional_item",
                            "optional_bitfield_name":"available",
                            "optional_bitfield_index":27,
                            "data_fields":[
                                {
                                    "name":"Age",
                                    "type":"fixed_bytes",
                                    "data_type":"uint",
                                    "length":1,
                                    "lsb":0.1
                                }
                            ]
                        },
                        {
                            "name":"Message Amplitude",
                            "type":"optional_item",
                            "optional_bitfield_name":"available",
                            "optional_bitfield_index":26,
                            "data_fields":[
                                {
                                    "name":"Age",
                                    "type":"fixed_bytes",
                                    "data_type":"uint",
                                    "length":1,
                                    "lsb":0.1
                                }
                            ]
                        },
                        {
                            "name":"Geometric Height",
                            "type":"optional_item",
                            "optional_bitfield_name":"available",
                            "optional_bitfield_index":25,
                            "data_fields":[
                                {
                                    "name":"Age",
                                    "type":"fixed_bytes",
                                    "data_type":"uint",
                                    "length":1,
                                    "lsb":0.1
                                }
                            ]
                        },
                        {
                            "name":"Flight Level",
                            "type":"optional_item",
                            "optional_bitfield_name":"available",
                            "optional_bitfield_index":23,
                            "data_fields":[
                                {
                                    "name":"age",
                                    "type":"fixed_bytes",
                                    "data_type":"uint",
                                    "length":1,
                                    "lsb":0.1
                                }
                            ]
                        },
                        {
                            "name":"Intermediate State Selected Altitude",
                            "type":"optional_item",
                            "optional_bitfield_name":"available",
                            "optional_bitfield_index":22,
                            "data_fields":[
                                {
                                    "name":"Age",
                                    "type":"fixed_bytes",
                                    "data_type":"uint",
                                    "length":1,
                                    "lsb":0.1
                                }
                            ]
                        },
                        {
                            "name":"Final State Selected Altitude",
                            "type":"optional_item",
                            "optional_bitfield_name":"available",
                            "optional_bitfield_index":21,
                            "data_fields":[
                                {
                                    "name":"Age",
                                    "type":"fixed_bytes",
                                    "data_type":"uint",
                                    "length":1,
                                    "lsb":0.1
                                }
                            ]
                        },
                        {
                            "name":"Air Speed",
                            "type":"optional_item",
                            "optional_bitfield_name":"available",
                            "optional_bitfield_index":20,
                            "data_fields":[
                                {
                                    "name":"Age",
                                    "type":"fixed_bytes",
                                    "data_type":"uint",
                                    "length":1,
                                    "lsb":0.1
                                }
                            ]
                        },
                        {
                            "name":"True Air Speed",
                            "type":"optional_item",
                            "optional_bitfield_name":"available",
                            "optional_bitfield_index":19,
                            "data_fields":[
                                {
                                    "name":"Age",
                                    "type":"fixed_bytes",
                                    "data_type":"uint",
                                    "length":1,
                                    "lsb":0.1
                                }
                            ]
                        },
                        {
                            "name":"Magnetic Heading",
                            "type":"optional_item",
                            "optional_bitfield_name":"available",
                            "optional_bitfield_index":18,
                            "data_fields":[
                                {
                                    "name":"Age",
                                    "type":"fixed_bytes",
                                    "data_type":"uint",
                                    "length":1,
                                    "lsb":0.1
                                }
                            ]
                        },
                        {
                            "name":"Barometric Vertical Rate",
                            "type":"optional_item",
                            "optional_bitfield_name":"available",
                            "optional_bitfield_index":17,
                            "data_fields":[
                                {
                                    "name":"Age",
                                    "type":"fixed_bytes",
                                    "data_type":"uint",
                                    "length":1,
                                    "lsb":0.1
                                }
                            ]
                        },
                        {
                            "name":"Geometric Vertical Rate",
                            "type":"optional_item",
                            "optional_bitfield_name":"available",
                            "optional_bitfield_index":15,
                            "data_fields":[
                                {
                                    "name":"Age",
                                    "type":"fixed_bytes",
                                    "data_type":"uint",
                                    "length":1,
                                    "lsb":0.1
                                }
                            ]
                        },
                        {
                            "name":"Ground Vector",
                            "type":"optional_item",
                            "optional_bitfield_name":"available",
                            "optional_bitfield_index":14,
                            "data_fields":[
                                {
                                    "name":"Age",
                                    "type":"fixed_bytes",
                                    "data_type":"uint",
                                    "length":1,
                                    "lsb":0.1
                                }
                            ]
                        },
                        {
                            "name":"Track Angle Rate",
                            "type":"optional_item",
                            "optional_bitfield_name":"available",
                            "optional_bitfield_index":13,
                            "data_fields":[
                                {
                                    "name":"Age",
                                    "type":"fixed_bytes",
                                    "data_type":"uint",
                                    "length":1,
                                    "lsb":0.1
                                }
                            ]
                        },
                        {
                            "name":"Target Identification",
                            "type":"optional_item",
                            "optional_bitfield_name":"available",
                            "optional_bitfield_index":12,
                            "data_fields":[
                                {
                                    "name":"Age",
                                    "type":"fixed_bytes",
                                    "data_type":"uint",
                                    "length":1,
                                    "lsb":0.1
                                }
                            ]
                        },
                        {
                            "name":"Target Status",
                            "type":"optional_item",
                            "optional_bitfield_name":"available",
                            "optional_bitfield_index":11,
                            "data_fields":[
                                {
                                    "name":"Age",
                                    "type":"fixed_bytes",
                                    "data_type":"uint",
                                    "length":1,
                                    "lsb":0.1
                                }
                            ]
                        },
                        {
                            "name":"Met Information",
                            "type":"optional_item",
                            "optional_bitfield_name":"available",
                            "optional_bitfield_index":10,
                            "data_fields":[
                                {
                                    "name":"Age",
                                    "type":"fixed_bytes",
                                    "data_type":"uint",
                                    "length":1,
                                    "lsb":0.1
                                }
                            ]
                        },
                        {
                            "name":"Roll Angle",
                            "type":"optional_item",
                            "optional_bitfield_name":"available",
                            "optional_bitfield_index":9,
                            "data_fields":[
                                {
                                    "name":"Age",
                                    "type":"fixed_bytes",
                                    "data_type":"uint",
                                    "length":1,
                                    "lsb":0.1
                                }
                            ]
                        },
                        {
                            "name":"ACAS Resolution Advisory",
                            "type":"optional_item",
                            "optional_bitfield_name":"available",
                            "optional_bitfield_index":7,
                            "data_fields":[
                                {
                                    "name":"Age",
                                    "type":"fixed_bytes",
                                    "data_type":"uint",
                                    "length":1,
                                    "lsb":0.1
                                }
                            ]
                        },
                        {
                            "name":"Surface Capabilities and Characteristics",
                            "type":"optional_item",
                            "optional_bitfield_name":"available",
                            "optional_bitfield_index":6,
                            "data_fields":[
                                {
                                    "name":"Age",
                                    "type":"fixed_bytes",
                                    "data_type":"uint",
                                    "length":1,
                                    "lsb":0.1
                                }
                            ]
                        }
                    ]
                }
            ]
        },
        {
            "name":"400",
            "type":"item",
            "data_fields":[
                {
                    "name":"RID",
                    "type":"fixed_bytes",
                    "length":1,
                    "data_type":"uint"
                }
            ]
        }
    ]
}
